jltest/__init__.py
jltest/app.py
jltest/sample.py
jltest/server.py
jltest-0.1.2.dist-info/LICENSE
jltest-0.1.2.dist-info/METADATA
jltest-0.1.2.dist-info/WHEEL
jltest-0.1.2.dist-info/top_level.txt
jltest-0.1.2.dist-info/RECORD
